pymorphy2_dicts/__init__.py
pymorphy2_dicts/version.py
pymorphy2_dicts/data/grammemes.json
pymorphy2_dicts/data/gramtab-opencorpora-ext.json
pymorphy2_dicts/data/gramtab-opencorpora-int.json
pymorphy2_dicts/data/meta.json
pymorphy2_dicts/data/p_t_given_w.intdawg
pymorphy2_dicts/data/paradigm-prefixes.json
pymorphy2_dicts/data/paradigms.array
pymorphy2_dicts/data/prediction-prefixes.dawg
pymorphy2_dicts/data/prediction-suffixes-0.dawg
pymorphy2_dicts/data/prediction-suffixes-1.dawg
pymorphy2_dicts/data/prediction-suffixes-2.dawg
pymorphy2_dicts/data/suffixes.json
pymorphy2_dicts/data/words.dawg
pymorphy2_dicts-2.4.393442.3710985.dist-info/DESCRIPTION.rst
pymorphy2_dicts-2.4.393442.3710985.dist-info/METADATA
pymorphy2_dicts-2.4.393442.3710985.dist-info/metadata.json
pymorphy2_dicts-2.4.393442.3710985.dist-info/RECORD
pymorphy2_dicts-2.4.393442.3710985.dist-info/top_level.txt
pymorphy2_dicts-2.4.393442.3710985.dist-info/WHEEL
